elbow/__init__.py
elbow/_version.py
elbow/builders.py
elbow/pipeline.py
elbow/record.py
elbow/typing.py
elbow/utils.py
elbow/dtypes/__init__.py
elbow/dtypes/_json.py
elbow/dtypes/_ndarray.py
elbow/dtypes/_pandas_array.py
elbow/dtypes/_pickle.py
elbow/dtypes/base.py
elbow/dtypes/inference.py
elbow/extractors/__init__.py
elbow/extractors/base.py
elbow/extractors/file_meta.py
elbow/filters/__init__.py
elbow/filters/meta.py
elbow/filters/partition.py
elbow/filters/patterns.py
elbow/sinks/__init__.py
elbow/sinks/parquet.py
elbow/sources/__init__.py
elbow/sources/filesystem.py
elbow-0.1.1.dist-info/LICENSE
elbow-0.1.1.dist-info/METADATA
elbow-0.1.1.dist-info/WHEEL
elbow-0.1.1.dist-info/top_level.txt
elbow-0.1.1.dist-info/RECORD
