Metadata-Version: 2.1
Name: elbow
Version: 0.1.1
Summary: Lift special-purpose data into common tabular formats for analytics 💪
Author-email: Connor Lane <connor.lane858@gmail.com>
License: MIT License
Project-URL: Homepage, https://github.com/cmi-dair/elbow
Classifier: Development Status :: 3 - Alpha
Classifier: Intended Audience :: Developers
Classifier: Topic :: Scientific/Engineering
Classifier: License :: OSI Approved :: MIT License
Classifier: Programming Language :: Python :: 3
Classifier: Programming Language :: Python :: 3.7
Classifier: Programming Language :: Python :: 3.8
Classifier: Programming Language :: Python :: 3.9
Classifier: Programming Language :: Python :: 3.10
Classifier: Programming Language :: Python :: 3.11
Requires-Python: >=3.7
License-File: LICENSE
Requires-Dist: typing-extensions
Requires-Dist: numpy
Requires-Dist: pandas
Requires-Dist: pyarrow
Requires-Dist: tqdm
Provides-Extra: dev
Requires-Dist: black ==23.3.0 ; extra == 'dev'
Requires-Dist: flake8 ==5.0.4 ; extra == 'dev'
Requires-Dist: isort ==5.11.5 ; extra == 'dev'
Requires-Dist: mypy ==1.2.0 ; extra == 'dev'
Requires-Dist: pre-commit ; extra == 'dev'
Requires-Dist: pylint >=2.5.0 ; extra == 'dev'
Requires-Dist: setuptools-scm ; extra == 'dev'
Provides-Extra: test
Requires-Dist: pytest ; extra == 'test'
Requires-Dist: pytest-cov ; extra == 'test'
Requires-Dist: pytest-benchmark ; extra == 'test'
